pyspark_data_prep/__init__.py
pyspark_data_prep/df_modifier.py
tests/__init__.py
tests/test_df_modifier.py
pyspark_data_prep-1.0.0.dist-info/METADATA
pyspark_data_prep-1.0.0.dist-info/WHEEL
pyspark_data_prep-1.0.0.dist-info/top_level.txt
pyspark_data_prep-1.0.0.dist-info/RECORD
